Metadata-Version: 1.0
Name: cocov
Version: 0.0.1
Summary: CoCo is a Code Convert tool which can transform file's encoding format.
Home-page: https://github.com/buptmiao/CoCo
Author: buptmiao
Author-email: buptmiao@163.com
License: MIT License
Platform: UNKNOWN
